update_docs/__init__.py
update_docs/cli.py
update_docs/core.py
update_docs/templates/Makefile
update_docs/templates/github_workflow.yml
update_docs/templates/pre_commit_hook.sh
update_docs/templates/setup_automation.sh
update_docs/templates/watch_docs.py
update_docs_system-1.0.4.dist-info/licenses/LICENSE
update_docs_system-1.0.4.dist-info/METADATA
update_docs_system-1.0.4.dist-info/WHEEL
update_docs_system-1.0.4.dist-info/entry_points.txt
update_docs_system-1.0.4.dist-info/top_level.txt
update_docs_system-1.0.4.dist-info/RECORD
