Metadata-Version: 2.4
Name: update-docs-system
Version: 1.0.4
Summary: Комплексная система автоматизации документации
Home-page: https://github.com/CoreTwin/docs_repo
Author: William Evans
Author-email: William Evans <we256681@gmail.com>
License-Expression: MIT
Project-URL: Homepage, https://github.com/CoreTwin/docs_repo
Project-URL: Documentation, https://github.com/CoreTwin/docs_repo/blob/main/README.md
Project-URL: Repository, https://github.com/CoreTwin/docs_repo.git
Project-URL: Issues, https://github.com/CoreTwin/docs_repo/issues
Keywords: documentation,markdown,automation,git
Classifier: Development Status :: 5 - Production/Stable
Classifier: Intended Audience :: Developers
Classifier: Topic :: Software Development :: Documentation
Classifier: Programming Language :: Python :: 3
Requires-Python: >=3.7
License-File: LICENSE
Requires-Dist: click>=8.0.0
Requires-Dist: gitpython>=3.1.0
Requires-Dist: watchdog>=2.1.0
Requires-Dist: requests>=2.25.0
Provides-Extra: dev
Requires-Dist: pytest>=6.0; extra == "dev"
Requires-Dist: pytest-cov>=2.0; extra == "dev"
Requires-Dist: black>=21.0; extra == "dev"
Requires-Dist: flake8>=3.8; extra == "dev"
Dynamic: author
Dynamic: home-page
Dynamic: license-file
Dynamic: requires-python
